ajax_select/LICENSE.txt
ajax_select/__init__.py
ajax_select/admin.py
ajax_select/apps.py
ajax_select/fields.py
ajax_select/helpers.py
ajax_select/lookup_channel.py
ajax_select/registry.py
ajax_select/urls.py
ajax_select/views.py
ajax_select/static/ajax_select/css/ajax_select.css
ajax_select/static/ajax_select/images/loading-indicator.gif
ajax_select/static/ajax_select/js/ajax_select.js
ajax_select/static/ajax_select/js/bootstrap.js
ajax_select/templates/ajax_select/autocomplete.html
ajax_select/templates/ajax_select/autocompleteselect.html
ajax_select/templates/ajax_select/autocompleteselectmultiple.html
lc_django_ajax_selects-1.7.1.1.dist-info/LICENSE
lc_django_ajax_selects-1.7.1.1.dist-info/METADATA
lc_django_ajax_selects-1.7.1.1.dist-info/WHEEL
lc_django_ajax_selects-1.7.1.1.dist-info/top_level.txt
lc_django_ajax_selects-1.7.1.1.dist-info/RECORD
